{
  "gitSyncId": "6a5e8e274f5d846e35c56d6b_58efe19e-c85e-4318-8e5b-0bd3bf143773",
  "id": "Page1_Select_public_leads1",
  "pluginId": "postgres-plugin",
  "pluginType": "DB",
  "unpublishedAction": {
    "actionConfiguration": {
      "body": "SELECT\n  *\nFROM\n  public.leads\nWHERE\n  \"nome\" ilike '%{{Table_leads.searchText}}%'\nORDER BY\n  \"{{Table_leads.sortOrder.column || 'id'}}\" {{Table_leads.sortOrder.order !== \"desc\" ? \"\" : \"DESC\"}}\nLIMIT\n  {{Table_leads.pageSize}}\nOFFSET\n  {{Table_leads.pageOffset}}",
      "encodeParamsToggle": true,
      "paginationType": "NONE",
      "pluginSpecifiedTemplates": [
        {
          "value": false
        }
      ],
      "timeoutInMillisecond": 10000
    },
    "confirmBeforeExecute": false,
    "datasource": {
      "id": "Trabalho_Final",
      "isAutoGenerated": false,
      "name": "Trabalho_Final",
      "pluginId": "postgres-plugin"
    },
    "dynamicBindingPathList": [
      {
        "key": "body"
      }
    ],
    "name": "Select_public_leads1",
    "pageId": "Page1",
    "runBehaviour": "AUTOMATIC",
    "userSetOnLoad": false
  }
}